reporter_utils/__init__.py
reporter_utils/_version.py
reporter_utils/extractions.py
reporter_utils-0.1.1.dist-info/LICENSE.txt
reporter_utils-0.1.1.dist-info/METADATA
reporter_utils-0.1.1.dist-info/WHEEL
reporter_utils-0.1.1.dist-info/top_level.txt
reporter_utils-0.1.1.dist-info/RECORD
